<?xml version="1.0" encoding="utf-8"?>
<!DOCTYPE hibernate-mapping PUBLIC "-//Hibernate/Hibernate Mapping DTD 3.0//EN"
"http://hibernate.sourceforge.net/hibernate-mapping-3.0.dtd">
<!-- 
    Mapping file autogenerated by MyEclipse Persistence Tools
-->
<hibernate-mapping>
    <class name="com.wxpt.site.entity.Surquestion" table="surquestion" catalog="wxpt1">
        <id name="surquestionId" type="java.lang.Integer">
            <column name="surquestion_id" />
            <generator class="identity" />
        </id>
        <property name="surquestionNumber" type="java.lang.String">
            <column name="surquestion_number" length="200" not-null="true" />
        </property>
        <property name="surquestionContent" type="java.lang.String">
            <column name="surquestion_content" length="1024" not-null="true" />
        </property>
        <property name="surquestionType" type="java.lang.Integer">
            <column name="surquestion_type" not-null="true" />
        </property>
        <property name="surquestionAddtime" type="java.lang.String">
            <column name="surquestion_addtime" length="200" />
        </property>
        <property name="surquestionUpdatetime" type="java.lang.String">
            <column name="surquestion_updatetime" length="200" />
        </property>
        <set name="suroptions" inverse="true">
            <key>
                <column name="surquestion_id" not-null="true" />
            </key>
            <one-to-many class="com.wxpt.site.entity.Suroption" />
        </set>
        <set name="surrecords" inverse="true">
            <key>
                <column name="surquestion_id" not-null="true" />
            </key>
            <one-to-many class="com.wxpt.site.entity.Surrecord" />
        </set>
    </class>
</hibernate-mapping>
